{"udata":[{"id":1,"name":"javohir","age":"21","kurs":"English","manba":"instagram"},{"id":2,"name":"javohir","age":"21","kurs":"English","manba":"whatsapp"},{"id":3,"name":"javohir","age":"21","kurs":"English","manba":"whatsapp"},{"id":4,"name":"salmonxon","age":"31","kurs":"English","manba":"instagram"},{"id":5,"name":"jahon","age":"22","kurs":"English","manba":"instagram"},{"id":6,"name":"suvares","age":"27","kurs":"English","manba":"instagram"},{"id":7,"name":"samandar","age":"1","kurs":"English","manba":"instagram"}]}